{
  "answerKey": "RUFFLET",
  "answerDisplay": "RUFFLET",
  "sourceType": "pokemon-species",
  "evidenceVersion": "bulbapedia-evidence-v3",
  "passMode": "first_pass",
  "status": "ok",
  "pageTitle": "Rufflet (Pokémon)",
  "pageUrl": "https://bulbapedia.bulbagarden.net/wiki/Rufflet_(Pok%C3%A9mon)",
  "pageId": 115999,
  "pageRevisionId": 4504690,
  "leadText": "Rufflet (Japanese: ワシボン Washibon) is a dual-type Normal/Flying Pokémon introduced in Generation V. It evolves into Braviary starting at level 54. In Hisui, it evolves into Hisuian Braviary starting at level 54.",
  "sections": [
    {
      "title": "Biology",
      "text": "Biology [ edit | edit source ] Rufflet is a small avian Pokémon with a blue body. A large white plume of feathers covers its head and three tail feathers extend from its lower back. The feathery ruff extends down past its neck, covering the upper third of its body. Its face is blue with five pointed tips, resembling a mask and crown in contrast to the white feathers surrounding it. Extending from its forehead is a large feather, which is red on the lower half and white on the upper half. The split between the two colors on the feather resembles a zigzag pattern. Rufflet's beak is short and wide, with large eyes on either side. Each eye has a thick black iris with a small white pupil. Its yellow legs and feet are large in comparison to the body. Each foot has four digits: one backwards, and three forwards. The thick, black talons on its feet are strong enough to break even the hardest of berries, and crack Shellder to consume their insides. Rufflet also preys on Spewpa . Rufflet is extremely aggressive from birth and knowingly provokes opponents larger and more powerful than itself, including its own parent to gain acceptance. It sees this as a means of quickly getting stronger. The more times Rufflet faints or gets injured, the stronger it becomes. Rufflet will start crying whenever it loses a battle. As a result of the harsh environment of Hisui , Rufflet gains an additional Psychic-type when it evolves into Hisuian Braviary . Rufflet is a male-only species. Evolution [ edit | edit source ] Rufflet evolves into Braviary . In Hisui , Rufflet evolves into Hisuian Braviary . Unevolved Rufflet Normal Flying → First Evolution Braviary Normal Flying → First Evolution Braviary Hisuian Form Psychic Flying"
    },
    {
      "title": "Game data",
      "text": "Contents 1 Game data 1.1 Pokédex entries 1.2 Game locations 1.2.1 In side games 1.3 Held items 1.4 Stats 1.4.1 Base stats 1.5 Type effectiveness 1.6 Learnset 1.6.1 By leveling up 1.6.2 By TM 1.6.3 By breeding 1.7 Side game data 1.8 Evolution data 1.9 Sprites Game data [ edit | edit source ] Pokédex entries [ edit | edit source ] This Pokémon was unavailable prior to Generation V. Generation V Unova B W : #133 Unova B2 W2 : #109 Black They crush berries with their talons. They bravely stand up to any opponent, no matter how strong it is. White They will challenge anything, even strong opponents, without fear. Their frequent fights help them become stronger. Black 2 It stands up to massive opponents, not out of courage, but out of recklessness. But that is how it gets stronger. White 2 Generation VI Central Kalos #— Coastal Kalos #— Mountain Kalos #— Hoenn #— X They crush berries with their talons. They bravely stand up to any opponent, no matter how strong it is. Y They will challenge anything, even strong opponents, without fear. Their frequent fights help them become stronger. Omega Ruby They crush berries with their talons. They bravely stand up to any opponent, no matter how strong it is. Alpha Sapphire They will challenge anything, even strong opponents, without fear. Their frequent fights help them become stronger. Generation VII Alola S M : #075 Alola US UM : #089 Kanto #— This Pokémon has no Pokédex entries in Let's Go, Pikachu! and Let's Go, Eevee! . Sun They pick fights indiscriminately. They grow stronger and more powerful each time they faint or are injured. Moon With its sharp claws, this Pokémon pierces its prey, and then it pecks at them. Although it also consumes berries, it's a carnivore at heart. Ultra Sun With its powerful legs and sturdy claws, it can crack even the hard shells of Shellder and pluck out their insides. Ultra Moon Known as a natural-born warrior, soon after its hatching, it will challenge its parent to a fight in order to gain their acceptance. Generation VIII Galar #281 Isle of Armor #179 Crown Tundra #— Sinnoh #— Hisui #221 This Pokémon has no Pokédex entries in Brilliant Diamond and Shining Pearl . Sword If it spies a strong Pokémon, Rufflet can't resist challenging it to a battle. But if Rufflet loses, it starts bawling. Shield A combative Pokémon, it's ready to pick a fight with anyone. It has talons that can crush hard berries. Legends: Arceus Its chick-like looks belie its hotheadedness. It challenges its parents at every opportunity, desperate to prove its strength. Generation IX Paldea #365 Kitakami #— Blueberry #32 Lumiose #— Hyperspace #— This Pokémon has no Pokédex entries in Legends: Z-A . Scarlet They pick fights indiscriminately. They grow stronger and more powerful each time they faint or are injured. Violet With its sharp claws, this Pokémon pierces its prey, and then it pecks at them. Although it also consumes berries, it's a carnivore at heart. Spin-off games Pokopia #— This Pokémon has no Pokédex entries in Pokopia . Rufflet in the Alola Pokédex Rufflet in the Paldea Pokédex Rufflet in the Blueberry Pokédex Game locations [ edit | edit source ] This Pokémon was unavailable prior to Generation V. Generation V Black Trade White Routes 10 and 11 , Victory Road , Village Bridge Black 2 Trade White 2 Route 23 Generation VI X Y Friend Safari ( Flying ) Omega Ruby Alpha Sapphire Mirage Mountain (north of Lilycove City ) Generation VII Sun Route 3 , Poké Pelago Moon Trade Ultra Sun Route 3 Ultra Moon Trade Let's Go Pikachu Let's Go Eevee Unobtainable Generation VIII Sword Route 8 , Stony Wilderness , Bridge Field Rolling Fields , East Lake Axewell ( Max Raid Battle ) Shield Trade Sword Expansion Pass Potbottom Desert Loop Lagoon ( Max Raid Battle ) Brilliant Diamond Shining Pearl Unobtainable Legends: Arceus Alabaster Icelands : near Avalugg's Legacy , Heart's Crag , Lake Acuity , near Pearl Settlement , massive mass outbreaks Generation IX Scarlet Violet South Province: Area One , Area Three , Area Four , Area Six East Province: Area Three West Province: Asado Desert North Province: Area One , Area Two , Dalizapa Passage , Glaseado Mountain Tera Raid Battles ( 3★ ) The Hidden Treasure of Area Zero Savanna Biome Legends: Z-A Unobtainable In side games [ edit | edit source ] This Pokémon was unavailable prior to Generation V. Generation V Rumble Blast Canyon: Rugged Flats Conquest Avia MD GTI Moonlit Forest (Uncharted Road), Rusty Mountain (Uncharted Road, Gilded Hall), Jaws of the Abyss (Gilded Hall), Smoking Mountain (Gilded Hall), Scalchop Beach (1F-14F), Kecleon Bazaar (1F-20F) Rumble U Secret Warehouse: Walking a Thin Line Generation VI Battle Trozei Safari Jungle: Stage 2 Sa Rumble World Dark Land: Boundless Prairie (All Areas) Generation VII Rumble Rush Aegislash Sea , Buzzwole Sea , Rayquaza Sea , Buzzwole Sea Final Generation VIII This Pokémon is unavailable in Generation VIII side games. Generation IX Sleep Greengrass Isle (from Great 1) Cyan Beach (from Basic 3) Snowdrop Tundra , Amber Canyon , Greengrass Isle Expert (from Basic 1) Cross-Generation Shuffle Wacky Workshop: Stage 171 Marron Trail: Stage 682 Held items [ edit | edit source ] Games Held items Legends: Arceus Normal Sootfoot Root (35%) Ball of Mud (15%) Grit items by level Alpha Exp. Candy S (100%) Seed of Mastery (10%) Grit items by level Stats [ edit | edit source ] Base stats [ edit | edit source ] Stat Range At Lv. 50 At Lv. 100 HP : 70 130 - 177 250 - 344 Attack : 83 79 - 148 153 - 291 Defense : 50 49 - 112 94 - 218 Sp. Atk : 37 37 - 97 71 - 190 Sp. Def : 50 49 - 112 94 - 218 Speed : 60 58 - 123 112 - 240 Total: 350 Other Pokémon with this total Minimum stats are calculated with 0 EVs , IVs of 0, and (if applicable) a hindering nature . Maximum stats are calculated with 252 EVs , IVs of 31, and (if applicable) a helpful nature . Type effectiveness [ edit | edit source ] Under normal battle conditions in Generation IX, this Pokémon is: Damaged normally by: Normal 1× Fighting 1× Flying 1× Poison 1× Ground 0× Rock 2× Bug ½× Ghost 0× Steel 1× Fire 1× Water 1× Grass ½× Electric 2× Psychic 1× Ice 2× Dragon 1× Dark 1× Fairy 1× None Weak to: Normal 1× Fighting 1× Flying 1× Poison 1× Ground 0× Rock 2× Bug ½× Ghost 0× Steel 1× Fire 1× Water 1× Grass ½× Electric 2× Psychic 1× Ice 2× Dragon 1× Dark 1× Fairy 1× None Immune to: Normal 1× Fighting 1× Flying 1× Poison 1× Ground 0× Rock 2× Bug ½× Ghost 0× Steel 1× Fire 1× Water 1× Grass ½× Electric 2× Psychic 1× Ice 2× Dragon 1× Dark 1× Fairy 1× None Resistant to: Normal 1× Fighting 1× Flying 1× Poison 1× Ground 0× Rock 2× Bug ½× Ghost 0× Steel 1× Fire 1× Water 1× Grass ½× Electric 2× Psychic 1× Ice 2× Dragon 1× Dark 1× Fairy 1× None Notes: If this Pokémon is given a Ring Target , the effectiveness of Ghost-type moves is 1×. If Gravity is in effect, this Pokémon is given an Iron Ball or a Ring Target , or it is affected by Smack Down or Ingrain , the effectiveness of Ground-type moves is 1×. Learnset [ edit | edit source ] Rufflet is available in Scarlet and Violet . By leveling up [ edit | edit source ] Generation IX Other generations: V - VI - VII - VIII Level Move Type Cat. Pwr. Acc. PP 01 1 Peck Flying Physical 035 35 100 100% 35 01 1 Leer Normal Status 0000 — 100 100% 30 06 6 Hone Claws Dark Status 0000 — 00— —% 15 12 12 Wing Attack Flying Physical 060 60 100 100% 35 18 18 Tailwind Flying Status 0000 — 00— —% 15 24 24 Scary Face Normal Status 0000 — 100 100% 10 30 30 Aerial Ace Flying Physical 060 60 00— —% 20 36 36 Slash Normal Physical 070 70 100 100% 20 42 42 Whirlwind Normal Status 0000 — 00— —% 20 48 48 Crush Claw Normal Physical 075 75 095 95% 10 55 55 Air Slash Flying Special 075 75 095 95% 15 60 60 Defog Flying Status 0000 — 00— —% 15 66 66 Thrash Normal Physical 120 120 100 100% 10 72 72 Brave Bird Flying Physical 120 120 100 100% 15 Bold indicates a move that gets STAB when used by Rufflet Italic indicates a move that gets STAB only when used by an Evolution of Rufflet Click on the generation numbers at the top to see level-up moves from other generations By TM [ edit | edit source ] Generation IX Other generations: V - VI - VII - VIII TM Move Type Cat. Pwr. Acc. PP TM001 TM001 Take Down Normal Physical 090 90 085}} 85% 20 TM004 TM004 Agility Psychic Status 0000 — 00—}} —% 30 TM006 TM006 Scary Face Normal Status 0000 — 100}} 100% 10 TM007 TM007 Protect Normal Status 0000 — 00—}} —% 10 TM014 TM014 Acrobatics Flying Physical 055 55 100}} 100% 15 TM025 TM025 Facade Normal Physical 070 70 100}} 100% 20 TM027 TM027 Aerial Ace Flying Physical 060 60 00—}} —% 20 TM032 TM032 Swift Normal Special 060 60 00—}} —% 20 TM036 TM036 Rock Tomb Rock Physical 060 60 095}} 95% 15 TM040 TM040 Air Cutter Flying Special 060 60 095}} 95% 25 TM047 TM047 Endure Normal Status 0000 — 00—}} —% 10 TM049 TM049 Sunny Day Fire Status 0000 — 00—}} —% 5 TM050 TM050 Rain Dance Water Status 0000 — 00—}} —% 5 TM059 TM059 Zen Headbutt Psychic Physical 080 80 090}} 90% 15 TM060 TM060 U-turn Bug Physical 070 70 100}} 100% 20 TM061 TM061 Shadow Claw Ghost Physical 070 70 100}} 100% 15 TM064 TM064 Bulk Up Fighting Status 0000 — 00—}} —% 20 TM065 TM065 Air Slash Flying Special 075 75 095}} 95% 15 TM066 TM066 Body Slam Normal Physical 085 85 100}} 100% 15 TM070 TM070 Sleep Talk Normal Status 0000 — 00—}} —% 10 TM085 TM085 Rest Psychic Status 0000 — 00—}} —% 5 TM086 TM086 Rock Slide Rock Physical 075 75 090}} 90% 10 TM097 TM097 Fly Flying Physical 090 90 095}} 95% 15 TM103 TM103 Substitute Normal Status 0000 — 00—}} —% 10 TM113 TM113 Tailwind Flying Status 0000 — 00—}} —% 15 TM118 TM118 Heat Wave Fire Special 095 95 090}} 90% 10 TM130 TM130 Helping Hand Normal Status 0000 — 00—}} —% 20 TM160 TM160 Hurricane Flying Special 110 110 070}} 70% 10 TM164 TM164 Brave Bird Flying Physical 120 120 100}} 100% 15 TM167 TM167 Close Combat Fighting Physical 120 120 100}} 100% 5 TM171 TM171 Tera Blast Normal Special 080 80 100}} 100% 10 TM197 TM197 Dual Wingbeat Flying Physical 040 40 090}} 90% 10 TM204 TM204 Double-Edge Normal Physical 120 120 100}} 100% 15 TM216 TM216 Feather Dance Flying Status 0000 — 100}} 100% 15 Bold indicates a move that gets STAB when used by Rufflet Italic indicates a move that gets STAB only when used by an Evolution or an alternate form of Rufflet Click on the generation numbers at the top to see TM moves from other generations By breeding [ edit | edit source ] Generation IX Other generations: V - VI - VII - VIII Parent Move Type Cat. Pwr. Acc. PP * Rock Smash Fighting Physical 40 100% 15 * Roost Flying Status — —% 5 Moves marked with an asterisk (*) must be chain bred onto Rufflet Bold indicates a move that gets STAB when used by Rufflet Italic indicates a move that gets STAB only when used by an Evolution of Rufflet Click on the generation numbers at the top to see Egg moves from other generations Side game data [ edit | edit source ] Pokémon Super Mystery Dungeon Body size: Standard (1 tile) How to Recruit : Introduced by Chandelure Connected to: Chandelure Connection Orb Set: 3 Phrases Normal I'm brave! I don't back down no matter who the opponent is! I mean it! Low HP ( Eep... I'm scared... Pokémon Rumble Blast Attack ●●● Defense ●● Speed ●●● Pokémon Rumble Rush Walking Speed: 1.45 seconds Base HP: 53 Base Attack: 72 Base Defense: 48 Base Speed: 60 Pokémon Conquest HP: ★★★ Move: Wing Attack Attack: ★★★ Ability 1: Keen Eye Ability 2: Pride Ability 3: Celebrate Defense: ★★ Speed: ★★ Evolves into Braviary when its Attack is 119 or higher Range: 4 Perfect Links: Haruyuki , Masamune , Munetoki , and Naoshige Pokémon Battle Trozei Flying Attack Power: ★ ★★★★ Pokémon Shuffle Flying Attack Power: 50 - 120 15 #213 Flap Delays your opponent's disruptions. Swappable Skill(s): Final Effort PSB drops : Main stage 682 Pokémon GO Base HP: 172 Base Attack: 150 Base Defense: 97 Egg Distance: 10 km Buddy Distance: 5 km Evolution Requirement: 50 Fast Attacks: Peck , Wing Attack Charged Attacks: Aerial Ace , Brave Bird , Rock Tomb , Fly * Pokémon Sleep Sleep type : Slumbering Pokémon type: Flying Points to befriend : 5 Specialty: Skills Berry: Pamtre Berry ×1 Primary ingredient : Bean Sausage ×1 Possible ingredients : Bean Sausage Greengrass Corn Rousing Coffee Main skill : Berry Burst Base carry limit: 10 Gets ? Berries plus ? of each of the Berries other Pokémon on your team collect Evolution requirements: Rufflet Candy ×40, Lv. 41 It picks fights indiscriminately and grows stronger and more powerful each time it faints. Although quite rare, you may see a sleeping Rufflet that looks like it's about to cry. It could be challenging a strong opponent in its dreams. Roosting Sleep Flutter Sleep Fussy Sleep Atop-Belly Sleep ★ ★★★★ ★★ ★★★ ★★★ ★★ ★★★★ ★ Evolution data [ edit | edit source ] Unevolved Rufflet Normal Flying Level 54 outside of Hisui → First Evolution Braviary Normal Flying + Level 54 in Hisui → First Evolution Braviary Hisuian Form Psychic Flying Sprites [ edit | edit source ] This Pokémon was unavailable prior to Generation V. Generation V Black White Black 2 White 2 Front Back Front Back Generation VI X Y Omega Ruby Alpha Sapphire Front Back Front Back Generation VII Sun Moon Ultra Sun Ultra Moon Front Back Front Back Generation VIII Sword Shield Legends: Arceus Cross-Generation HOME For other sprites and images, please see Rufflet images on the Bulbagarden Archives ."
    },
    {
      "title": "Pokédex entries",
      "text": "Pokédex entries [ edit | edit source ] This Pokémon was unavailable prior to Generation V. Generation V Unova B W : #133 Unova B2 W2 : #109 Black They crush berries with their talons. They bravely stand up to any opponent, no matter how strong it is. White They will challenge anything, even strong opponents, without fear. Their frequent fights help them become stronger. Black 2 It stands up to massive opponents, not out of courage, but out of recklessness. But that is how it gets stronger. White 2 Generation VI Central Kalos #— Coastal Kalos #— Mountain Kalos #— Hoenn #— X They crush berries with their talons. They bravely stand up to any opponent, no matter how strong it is. Y They will challenge anything, even strong opponents, without fear. Their frequent fights help them become stronger. Omega Ruby They crush berries with their talons. They bravely stand up to any opponent, no matter how strong it is. Alpha Sapphire They will challenge anything, even strong opponents, without fear. Their frequent fights help them become stronger. Generation VII Alola S M : #075 Alola US UM : #089 Kanto #— This Pokémon has no Pokédex entries in Let's Go, Pikachu! and Let's Go, Eevee! . Sun They pick fights indiscriminately. They grow stronger and more powerful each time they faint or are injured. Moon With its sharp claws, this Pokémon pierces its prey, and then it pecks at them. Although it also consumes berries, it's a carnivore at heart. Ultra Sun With its powerful legs and sturdy claws, it can crack even the hard shells of Shellder and pluck out their insides. Ultra Moon Known as a natural-born warrior, soon after its hatching, it will challenge its parent to a fight in order to gain their acceptance. Generation VIII Galar #281 Isle of Armor #179 Crown Tundra #— Sinnoh #— Hisui #221 This Pokémon has no Pokédex entries in Brilliant Diamond and Shining Pearl . Sword If it spies a strong Pokémon, Rufflet can't resist challenging it to a battle. But if Rufflet loses, it starts bawling. Shield A combative Pokémon, it's ready to pick a fight with anyone. It has talons that can crush hard berries. Legends: Arceus Its chick-like looks belie its hotheadedness. It challenges its parents at every opportunity, desperate to prove its strength. Generation IX Paldea #365 Kitakami #— Blueberry #32 Lumiose #— Hyperspace #— This Pokémon has no Pokédex entries in Legends: Z-A . Scarlet They pick fights indiscriminately. They grow stronger and more powerful each time they faint or are injured. Violet With its sharp claws, this Pokémon pierces its prey, and then it pecks at them. Although it also consumes berries, it's a carnivore at heart. Spin-off games Pokopia #— This Pokémon has no Pokédex entries in Pokopia . Rufflet in the Alola Pokédex Rufflet in the Paldea Pokédex Rufflet in the Blueberry Pokédex"
    },
    {
      "title": "Pokédex entries",
      "text": "Pokédex entries [ edit | edit source ] Episode Pokémon Source Entry BW095 Rufflet Ash's Pokédex Rufflet, the Eaglet Pokémon. Rufflet's talons are powerful, able to crack open even the toughest Berries . It often challenges stronger opponents to battle."
    }
  ],
  "familyPages": [],
  "titleCandidates": [
    "Rufflet",
    "Rufflet (Pokemon)",
    "Rufflet (Pokémon)",
    "Rufflet (species)"
  ],
  "updatedAt": 1773326562
}