{
  "answerKey": "VICTREEBEL",
  "answerDisplay": "VICTREEBEL",
  "sourceType": "pokemon-species",
  "evidenceVersion": "bulbapedia-evidence-v3",
  "passMode": "first_pass",
  "status": "ok",
  "pageTitle": "Victreebel (Pokémon)",
  "pageUrl": "https://bulbapedia.bulbagarden.net/wiki/Victreebel_(Pok%C3%A9mon)",
  "pageId": 2409,
  "pageRevisionId": 4500806,
  "leadText": "Victreebel (Japanese: ウツボット Utsubot) is a dual-type Grass/Poison Pokémon introduced in Generation I. It evolves from Weepinbell when exposed to a Leaf Stone. It is the final form of Bellsprout. Victreebel can Mega Evolve into Mega Victreebel using the Victreebelite. Mega Victreebel was introduced in Pokémon Legends: Z-A.",
  "sections": [
    {
      "title": "Biology",
      "text": "Biology [ edit | edit source ] Victreebel is a pitcher plant Pokémon with a bell-shaped body. It has a gaping mouth with a swollen pink lip and two sharp teeth on the bottom. Its semicircular eyes appear directly under its mouth and it has several dark green spots on its body. On either side of its body is a large green leaf. Covering Victreebel's mouth is a leaf with a long, brown, yellow-tipped vine growing out of it. The acid produced by Victreebel can corrode any material, regardless of its hardness. Victreebel is said to live in huge colonies deep in jungles, although no one has ever returned from there. Being the result of exposure to an Evolution stone , Victreebel is rarely found in the wild, though they can be found in temperate forests and jungles . The vine on its leaf is flicked to mimic an animal in order to attract prey. It also produces a sweet scent of nectar or honey to further aid in luring its victims. Acid that has dissolved numerous prey becomes sweeter and even more effective at attracting prey. In the Pokémon Adventures chapter A Hollow Victreebel , Victreebel hoards food, usually small birds and rodents, and collects Leaf Stones to perform Evolution rituals at night to help Weepinbell become Victreebel as well. As mentioned in Pokémon Sleep , Victreebel is known to sleep with its mouth open to draw in prey. [ 1 ] Very rarely however, it forgets about luring in prey and instead chooses to sleep face down. Forms [ edit | edit source ] Mega Victreebel opening its mouth when using Sludge Bomb [ 2 ] Victreebel can Mega Evolve into Mega Victreebel. Mega Victreebel's body is massive compared to regular Victreebel, standing at almost three times its height and weighing over eight times as much. Its most distinctive feature is its bloated body, which is filled with large amounts of acid that Mega Victreebel creates thanks to the energy of Mega Evolution. The amount of acid in Mega Victreebel's body is so large that even closing its mouth is not enough to contain it, [ 2 ] so it has to wrap its throat with its own elongated vine in order to prevent the acid from spilling out. [ 3 ] Other notable physical features of Mega Victreebel include green leaves with orange tips on the sides of its body, and three large leaves on the tip of its vine hovering over its head, which also have orange tips. Due to the overflowing acid inside Mega Victreebel's body, it no longer catches prey by sitting still with its mouth open. Instead, it aggressively chases down prey by hopping about, landing destructive tackles with its body. The matured acid has a dizzying sweet scent, which Mega Victreebel uses to immobilize opponents by fanning the fumes towards them with the leaves on top of its head. It can employ the acid offensively, easily dissolving concrete or steel. [ 3 ] When Mega Victreebel opens its mouth to unleash its acid, its deflated appearance briefly resembles Victreebel's normal form. [ 2 ] Mega Victreebel Evolution [ edit | edit source ] Victreebel evolves from Weepinbell and is the final form of Bellsprout . (For specifics on this Pokémon's Evolution in the games, refer to Game data→Evolution data .) Unevolved Bellsprout Grass Poison → First Evolution Weepinbell Grass Poison → Second Evolution Victreebel Grass Poison ↑ Sleep Style Dex ↑ 2.0 2.1 2.2 (August 21, 2025). Pokémon Legends: Z-A | Mega Victreebel Bounds into Battle — Pokémon Official Website ↑ 3.0 3.1 Pokémon Legends: Z-A | Mega Victreebel — Pokémon Official Website"
    },
    {
      "title": "Game data",
      "text": "Contents 1 Game data 1.1 Pokédex entries 1.2 Game locations 1.2.1 In side games 1.3 Held items 1.4 Stats 1.4.1 Base stats 1.4.1.1 Victreebel 1.4.1.1.1 Generations I-V 1.4.1.1.2 Generation VI onward 1.4.1.2 Mega Victreebel 1.4.2 Pokéathlon stats 1.5 Type effectiveness 1.6 Learnset 1.6.1 By leveling up 1.6.2 By TM 1.6.3 By breeding 1.6.4 By a prior Evolution 1.6.5 Animated series-only moves 1.7 Side game data 1.7.1 Victreebel 1.7.2 Mega Victreebel 1.8 Form data 1.8.1 Mega Evolution 1.9 Evolution data 1.10 Sprites Game data [ edit | edit source ] Pokédex entries [ edit | edit source ] Generation I Kanto #071 Red (JPN) (This entry was originally untranslated in English until it was reused in Pokémon FireRed .) Green Red (ENG) Said to live in huge colonies deep in jungles, although no one has ever returned from there. Blue Yellow Lures prey with the sweet aroma of honey. Swallowed whole, the prey is melted in a day, bones and all. Stadium Attracts prey with sweet-smelling honey. Its prey include bugs, naturally, and even large animals on occasion. Generation II Johto #066 Gold Acid that has dissolved many prey becomes sweeter, making it even more effective at attracting prey. Silver This horrifying plant Pok é mon attracts prey with aromatic honey, then melts them in its mouth. Crystal Once ingested into this Pok é mon 's body, even the hardest object will melt into nothing. Stadium 2 Acid that has dissolved many prey becomes sweeter, making it even more effective at attracting prey. (Pokémon Red, Silver, or Crystal inserted) This horrifying plant Pok é mon attracts prey with aromatic honey, then melts them in its mouth. (Pokémon Blue, Gold, or Yellow inserted) Generation III Hoenn #— Kanto #071 Ruby Victreebel has a long vine that extends from its head. This vine is waved and flicked about as if it were an animal to attract prey. When an unsuspecting prey draws near, this Pok é mon swallows it whole. Sapphire Emerald The long vine extending from its head is waved about as if it were a living thing to attract prey. When an unsuspecting victim approaches, it is swallowed whole. FireRed Lures prey into its mouth with a honeylike aroma. The helpless prey is melted with a dissolving fluid. LeafGreen Said to live in huge colonies deep in jungles, although no one has ever returned from there. Generation IV Sinnoh #— Johto #066 Diamond It pools in its mouth a fluid with a honeylike scent, which is really an acid that dissolves anything. Pearl Platinum HeartGold Acid that has dissolved many prey becomes sweeter, making it even more effective at attracting prey. SoulSilver This horrifying plant Pokémon attracts prey with aromatic honey, then melts them in its mouth. Generation V Unova #— Black It pools in its mouth a fluid with a honeylike scent, which is really an acid that dissolves anything. White Black 2 It pools in its mouth a fluid with a honey-like scent, which is really an acid that dissolves anything. White 2 Generation VI Central Kalos #— Coastal Kalos #— Mountain Kalos #028 Hoenn #— X Said to live in huge colonies deep in jungles, although no one has ever returned from there. Y Once ingested into this Pokémon's body, even the hardest object will melt into nothing. Omega Ruby Victreebel has a long vine that extends from its head. This vine is waved and flicked about as if it were an animal to attract prey. When an unsuspecting prey draws near, this Pokémon swallows it whole. Alpha Sapphire Generation VII Alola #— Kanto #071 This Pokémon has no Pokédex entries in Sun, Moon , Ultra Sun, and Ultra Moon . Let's Go Pikachu Lures prey with the sweet aroma of honey. Swallowed whole, the prey is dissolved in a day, bones and all. Let's Go Eevee Generation VIII Galar #— Isle of Armor #— Crown Tundra #— Sinnoh #— Hisui #— This Pokémon has no Pokédex entries in Sword, Shield , and Legends: Arceus . Brilliant Diamond In its mouth, it pools a fragrant nectar-like fluid. The fluid is really an acid that dissolves anything. Shining Pearl Generation IX Paldea #— Kitakami #25 Blueberry #— Lumiose #076 Hyperspace #— Scarlet It lures prey into its mouth with a nectar-like aroma. The helpless prey is melted with a dissolving fluid. Violet After dissolving many prey, this Pokémon's acid becomes sweeter. This makes it even easier to attract more prey. Legends: Z-A Once taken into Victreebel's body, even the hardest object will be melted into nothing by the Pokémon's acid. Mega Victreebel Legends: Z-A The volume of this Pokémon's acid has increased due to Mega Evolution, filling its mouth. If it's not careful, the acid will overflow and spill out. Spin-off games Pokopia #023 Pokopia After dissolving many prey, this Pokémon's acid becomes sweeter. This makes it even easier to attract more prey. Victreebel in the Kitakami Pokédex Game locations [ edit | edit source ] Generation I Red Trade Blue Evolve Weepinbell Blue (Japan) Trade Yellow Evolve Weepinbell Generation II Gold Silver Evolve Weepinbell Crystal Evolve Weepinbell Generation III Ruby Sapphire Trade Emerald Trade FireRed Trade LeafGreen Evolve Weepinbell Colosseum Trade XD Evolve Weepinbell Generation IV Diamond Pearl Evolve Weepinbell Platinum Evolve Weepinbell HeartGold SoulSilver Evolve Weepinbell Pal Park Forest Generation V Black Trade White Evolve Weepinbell Black 2 White 2 Trade Generation VI X Y Evolve Weepinbell Omega Ruby Alpha Sapphire Trade Generation VII Sun Moon Evolve Weepinbell Ultra Sun Ultra Moon Trade Let's Go Pikachu Trade Let's Go Eevee Route 21 Generation VIII Sword Shield Unobtainable Brilliant Diamond Shining Pearl Evolve Weepinbell Legends: Arceus Unobtainable Generation IX Scarlet Violet Trade Version 2.0.1+ The Hidden Treasure of Area Zero Tera Raid Battles ( 5★ ) Legends: Z-A Centrico Plaza : Wild Zone 20 In side games [ edit | edit source ] Generation I Snap Cave Pinball Evolve Weepinbell Generation II This Pokémon is unavailable in Generation II side games. Generation III Trozei! Endless Level 14, Forever Level 63, Pair Trozei, Mr. Who's Den MD Red MD Blue Evolve Weepinbell Ranger Lyra Forest Generation IV MD Time MD Darkness Mystery Jungle (1F-29F) MD Sky Mystery Jungle (1F-29F) Ranger: SoA Hippowdon Temple Rumble Windy Prairie (Normal Mode A & S) MD Light Evolve Weepinbell Generation V Rumble Blast Treetops: Soothing Shore Rumble U Chill Battle: Garden Keepers Generation VI Battle Trozei Safari Jungle: Stage 3 Tu Rumble World Distortion Land: Breezy Grasslands (All Areas, Entrance Boss) Generation VII Rumble Rush Charizard Sea 2019 , Bulbasaur Sea , Charizard Sea Final Generation VIII MD DX Joyous Tower (51F-55F) Fainted Pokémon: Fantasy Strait Generation IX Sleep Greengrass Isle (from Master 2) Lapis Lakeside (from Ultra 1) Cross-Generation Shuffle Zaffiro Coast: Stage 630 Masters EX Evolution : Ramos & Weepinbell , Scottie / Bettie & Weepinbell Egg Held items [ edit | edit source ] Pokémon caught in Generation I must be traded to a Generation II game in order for a held item to appear. Games Held items Red Blue Bitter Berry (100%) Yellow Stats [ edit | edit source ] Base stats [ edit | edit source ] Victreebel [ edit | edit source ] Generations I-V [ edit | edit source ] Stat Range At Lv. 50 At Lv. 100 HP : 80 140 - 187 270 - 364 Attack : 105 99 - 172 193 - 339 Defense : 65 63 - 128 121 - 251 Sp. Atk : 100 94 - 167 184 - 328 Sp. Def : 60 58 - 123 112 - 240 Speed : 70 67 - 134 130 - 262 Total: 480 Other Pokémon with this total Minimum stats are calculated with 0 EVs , IVs of 0, and (if applicable) a hindering nature . Maximum stats are calculated with 252 EVs , IVs of 31, and (if applicable) a helpful nature . This Pokémon's Special base stat in Generation I was 100 . Generation VI onward [ edit | edit source ] Stat Range At Lv. 50 At Lv. 100 HP : 80 140 - 187 270 - 364 Attack : 105 99 - 172 193 - 339 Defense : 65 63 - 128 121 - 251 Sp. Atk : 100 94 - 167 184 - 328 Sp. Def : 70 67 - 134 130 - 262 Speed : 70 67 - 134 130 - 262 Total: 490 Other Pokémon with this total Minimum stats are calculated with 0 EVs , IVs of 0, and (if applicable) a hindering nature . Maximum stats are calculated with 252 EVs , IVs of 31, and (if applicable) a helpful nature . Mega Victreebel [ edit | edit source ] Stat Range At Lv. 50 At Lv. 100 HP : 80 140 - 187 270 - 364 Attack : 125 117 - 194 229 - 383 Defense : 85 81 - 150 157 - 295 Sp. Atk : 135 126 - 205 247 - 405 Sp. Def : 95 90 - 161 175 - 317 Speed : 70 67 - 134 130 - 262 Total: 590 Other Pokémon with this total Minimum stats are calculated with 0 EVs , IVs of 0, and (if applicable) a hindering nature . Maximum stats are calculated with 252 EVs , IVs of 31, and (if applicable) a helpful nature . Pokéathlon stats [ edit | edit source ] Speed 1/1 ★ Power 4/4 ★★★★ Skill 3/4 ★★★ ☆ Stamina 4/4 ★★★★ Jump 3/3 ★★★ Total 15/16 ★★★ Type effectiveness [ edit | edit source ] Under normal battle conditions in Generation IX, this Pokémon is: Damaged normally by: Normal 1× Fighting ½× Flying 2× Poison 1× Ground 1× Rock 1× Bug 1× Ghost 1× Steel 1× Fire 2× Water ½× Grass ¼× Electric ½× Psychic 2× Ice 2× Dragon 1× Dark 1× Fairy ½× None Weak to: Normal 1× Fighting ½× Flying 2× Poison 1× Ground 1× Rock 1× Bug 1× Ghost 1× Steel 1× Fire 2× Water ½× Grass ¼× Electric ½× Psychic 2× Ice 2× Dragon 1× Dark 1× Fairy ½× None Immune to: Normal 1× Fighting ½× Flying 2× Poison 1× Ground 1× Rock 1× Bug 1× Ghost 1× Steel 1× Fire 2× Water ½× Grass ¼× Electric ½× Psychic 2× Ice 2× Dragon 1× Dark 1× Fairy ½× None Resistant to: Normal 1× Fighting ½× Flying 2× Poison 1× Ground 1× Rock 1× Bug 1× Ghost 1× Steel 1× Fire 2× Water ½× Grass ¼× Electric ½× Psychic 2× Ice 2× Dragon 1× Dark 1× Fairy ½× None Notes: In Generation I , the effectiveness of Bug-type moves is 4×. Learnset [ edit | edit source ] Victreebel is available in Scarlet and Violet Version 2.0.1+ and Legends: Z-A . By leveling up [ edit | edit source ] S V Generation IX Other generations: I - II - III - IV - V - VI - VII - VIII Level Move Type Cat. Pwr. Acc. PP 01 1 Vine Whip Grass Physical 045 45 100 100% 25 01 1 Sleep Powder Grass Status 0000 — 075 75% 15 01 1 Sweet Scent Normal Status 0000 — 100 100% 20 01 1 Razor Leaf Grass Physical 055 55 095 95% 25 Rem. Rem. Stockpile Normal Status 0000 — — —% 20 Rem. Rem. Swallow Normal Status 0000 — — —% 10 Rem. Rem. Spit Up Normal Special 0000 — 100 100% 10 Rem. Rem. Gastro Acid Poison Status 0000 — 100 100% 10 Rem. Rem. Power Whip Grass Physical 120 120 085 85% 10 Evo. Evo. Leaf Storm Grass Special 130 130 090 90% 5 44 44 Leaf Blade Grass Physical 090 90 100 100% 15 Bold indicates a move that gets STAB when used by Victreebel Italic indicates a move that gets STAB only when used by an Evolution of Victreebel Click on the generation numbers at the top to see level-up moves from other generations ZA Generation IX Other generations: I - II - III - IV - V - VI - VII - VIII Learn Plus Move Type Cat. Power CD 1 10 Lunge Bug Physical 080 80 9 1 10 Vine Whip Grass Physical 045 45 6 1 10 Growth Grass Status 0000 — 15 Evo. 10 Sludge Bomb Poison Special 090 90 7 8 11 Infestation Bug Special 020 20 6 10 13 Razor Leaf Grass Physical 055 55 6 13 16 Sleep Powder Grass Status 0000 — 10 15 18 Poison Powder Poison Status 0000 — 10 17 20 Stun Spore Grass Status 0000 — 10 19 22 Knock Off Dark Physical 065 65 10 23 26 Magical Leaf Grass Special 060 60 6 26 29 Toxic Spikes Poison Status 0000 — 7 30 33 Poison Jab Poison Physical 080 80 8 33 36 Leech Life Bug Physical 080 80 9 40 43 Sludge Wave Poison Special 095 95 8 44 47 Power Whip Grass Physical 120 120 12 48 51 Leaf Storm Grass Special 130 130 10 Bold indicates a move that gets STAB when used by Victreebel Italic indicates a move that gets STAB only when used by an Evolution of Victreebel Click on the generation numbers at the top to see level-up moves from other generations By TM [ edit | edit source ] S V Generation IX Other generations: I - II - III - IV - V - VI - VII - VIII TM Move Type Cat. Pwr. Acc. PP TM006 TM006 Scary Face Normal Status 0000 — 100}} 100% 10 TM007 TM007 Protect Normal Status 0000 — 00—}} —% 10 TM013 TM013 Acid Spray Poison Special 040 40 100}} 100% 20 TM018 TM018 Thief Dark Physical 060 60 100}} 100% 25 TM020 TM020 Trailblaze Grass Physical 050 50 100}} 100% 20 TM021 TM021 Pounce Bug Physical 050 50 100}} 100% 20 TM025 TM025 Facade Normal Physical 070 70 100}} 100% 20 TM032 TM032 Swift Normal Special 060 60 00—}} —% 20 TM033 TM033 Magical Leaf Grass Special 060 60 00—}} —% 20 TM045 TM045 Venoshock Poison Special 065 65 100}} 100% 10 TM047 TM047 Endure Normal Status 0000 — 00—}} —% 10 TM049 TM049 Sunny Day Fire Status 0000 — 00—}} —% 5 TM056 TM056 Bullet Seed Grass Physical 025 25 100}} 100% 30 TM066 TM066 Body Slam Normal Physical 085 85 100}} 100% 15 TM070 TM070 Sleep Talk Normal Status 0000 — 00—}} —% 10 TM071 TM071 Seed Bomb Grass Physical 080 80 100}} 100% 15 TM074 TM074 Reflect Psychic Status 0000 — 00—}} —% 20 TM081 TM081 Grass Knot Grass Special 0000 — 100}} 100% 20 TM083 TM083 Poison Jab Poison Physical 080 80 100}} 100% 20 TM085 TM085 Rest Psychic Status 0000 — 00—}} —% 5 TM088 TM088 Swords Dance Normal Status 0000 — 00—}} —% 20 TM095 TM095 Leech Life Bug Physical 080 80 100}} 100% 10 TM103 TM103 Substitute Normal Status 0000 — 00—}} —% 10 TM111 TM111 Giga Drain Grass Special 075 75 100}} 100% 10 TM119 TM119 Energy Ball Grass Special 090 90 100}} 100% 10 TM122 TM122 Encore Normal Status 0000 — 100}} 100% 5 TM137 TM137 Grassy Terrain Grass Status 0000 — 00—}} —% 10 TM148 TM148 Sludge Bomb Poison Special 090 90 100}} 100% 10 TM152 TM152 Giga Impact Normal Physical 150 150 090}} 90% 5 TM159 TM159 Leaf Storm Grass Special 130 130 090}} 90% 5 TM163 TM163 Hyper Beam Normal Special 150 150 090}} 90% 5 TM168 TM168 Solar Beam Grass Special 120 120 100}} 100% 10 TM171 TM171 Tera Blast Normal Special 080 80 100}} 100% 10 TM175 TM175 Toxic Poison Status 0000 — 090}} 90% 10 TM181 TM181 Knock Off Dark Physical 065 65 100}} 100% 20 TM182 TM182 Bug Bite Bug Physical 060 60 100}} 100% 20 TM185 TM185 Lunge Bug Physical 080 80 100}} 100% 15 TM193 TM193 Weather Ball Normal Special 050 50 100}} 100% 10 TM194 TM194 Grassy Glide Grass Physical 055 55 100}} 100% 20 TM214 TM214 Sludge Wave Poison Special 095 95 100}} 100% 10 Bold indicates a move that gets STAB when used by Victreebel Italic indicates a move that gets STAB only when used by an Evolution or an alternate form of Victreebel Click on the generation numbers at the top to see TM moves from other generations ZA Generation IX Other generations: I - II - III - IV - V - VI - VII - VIII TM Move Type Cat. Pwr. CD TM007 TM007 Toxic Poison Status 0000 — 10 TM017 TM017 Protect Normal Status 0000 — 15 TM026 TM026 Energy Ball Grass Special 090 90 8 TM030 TM030 Swords Dance Normal Status 0000 — 15 TM031 TM031 Reflect Psychic Status 0000 — 12 TM035 TM035 Endure Normal Status 0000 — 12 TM040 TM040 Bullet Seed Grass Physical 015 15 6 TM042 TM042 Giga Drain Grass Special 075 75 9 TM044 TM044 Hyper Beam Normal Special 150 150 20 TM045 TM045 Knock Off Dark Physical 065 65 10 TM053 TM053 Sludge Bomb Poison Special 090 90 7 TM055 TM055 Giga Impact Normal Physical 150 150 20 TM064 TM064 Solar Beam Grass Special 120 120 12 TM077 TM077 Poison Jab Poison Physical 080 80 8 TM085 TM085 Substitute Normal Status 0000 — 10 TM089 TM089 Toxic Spikes Poison Status 0000 — 7 TM109 TM109 Facade Normal Physical 070 70 7 TM112 TM112 Acid Spray Poison Special 040 40 7 TM115 TM115 Trailblaze Grass Physical 040 40 6 TM128 TM128 Seed Bomb Grass Physical 035 35 7 Bold indicates a move that gets STAB when used by Victreebel Italic indicates a move that gets STAB only when used by an Evolution or an alternate form of Victreebel Click on the generation numbers at the top to see TM moves from other generations By breeding [ edit | edit source ] Generation IX Other generations: II - III - IV - V - VI - VII - VIII Parent Move Type Cat. Pwr. Acc. PP Clear Smog Poison Special 50 —% 15 Ingrain Grass Status — —% 20 * Strength Sap Grass Status — 100% 10 Sucker Punch Dark Physical 70 100% 5 Synthesis Grass Status — —% 5 Tickle * Normal Status — 100% 20 Worry Seed Grass Status — 100% 10 Moves marked with an asterisk (*) must be chain bred onto Victreebel Bold indicates a move that gets STAB when used by Victreebel Italic indicates a move that gets STAB only when used by an Evolution of Victreebel Click on the generation numbers at the top to see Egg moves from other generations By a prior Evolution [ edit | edit source ] S V Generation IX Other generations: I - II - III - IV - V - VI - VII - VIII Stage Move Type Cat. Pwr. Acc. PP Growth Normal Status — —% 20 Wrap Normal Physical 15 90% 20 Poison Powder Poison Status — 75% 35 Stun Spore Grass Status — 75% 30 Acid Poison Special 40 100% 30 Slam Normal Physical 80 75% 20 Bold indicates a move that gets STAB when used by Victreebel Italic indicates a move that gets STAB only when used by an Evolution of Victreebel Click on the generation numbers at the top to see moves from other generations ZA Generation IX Other generations: I - II - III - IV - V - VI - VII - VIII Stage Move Type Cat. Pwr. Acc. PP This Pokémon has no moves exclusive to prior Evolutions. Bold indicates a move that gets STAB when used by Weepinbell Italic indicates a move that gets STAB only when used by an Evolution of Weepinbell Click on the generation numbers at the top to see moves from other generations Animated series-only moves [ edit | edit source ] Move Type Episode Tackle Normal Pikachu Re-Volts Side game data [ edit | edit source ] Victreebel [ edit | edit source ] Pokémon Pinball Acquisition: Evolve Pokémon Trozei! Rarity: Rare Pokémon Mystery Dungeon Red Rescue Team and Blue Rescue Team Body size: 1 Recruit rate : Evolve Friend Area : Jungle Phrases 61%-100% HP Nothing gets out of my mouth alive! 26%-60% HP Listen, my HP's half gone. 1%-25% HP I'm wilting... My own acid is consuming me... Level up Yes, yes, I've leveled up! Pokémon Mystery Dungeon Explorers of Time, Explorers of Darkness , and Explorers of Sky Body size: 1 Recruit rate : -12% IQ group : G Pokémon Super Mystery Dungeon Body size: Standard (1 tile) How to Recruit : Give an Apple to in a dungeon Connected to: Tentacruel , Deino Connection Orb Set: 4 Phrases Normal Once in my mouth, anything delicious quickly drops into my belly! Low HP ( I've run out of energy... Pokémon Ranger Group: Grass Poké Assist: Poison Field move: None Loops: 7 Min. exp.: 62 Max. exp.: 96 Browser entry R-006 Victreebel sloshes poison from its big mouth. Beware of the puddled poison! Pokémon Ranger: Shadows of Almia Group: Grass Poké Assist: Grass Field move: (Cut ×2) Browser entry R-242 It shoots leaves and slops poison around to attack. Pokémon Rumble Attack ●●● Defense ●● Speed ●●● Pokémon Rumble Blast Attack ●●● Defense ●● Speed ●●● Pokémon Rumble Rush Walking Speed: 1.2 seconds Base HP: 55 Base Attack: 79 Base Defense: 52 Base Speed: 60 Pokémon Battle Trozei Grass Attack Power: ★★★ ★★ Pokémon Shuffle Grass Attack Power: 60 - 105 5 #654 Hitting Streak+ Deals even more damage the more times in a row it is triggered. Pokémon GO Base HP: 190 Base Attack: 207 Base Defense: 135 Egg Distance: N/A Buddy Distance: 3 km Evolution Requirement: 300 / 60 / 30 / 15 Fast Attacks: Razor Leaf , Acid , Magical Leaf † Charged Attacks: Leaf Blade , Sludge Bomb , Solar Beam , Leaf Tornado * , Acid Spray * , Frustration , Return Pokémon Sleep Sleep type : Dozing Pokémon type: Grass Points to befriend : 20 Specialty: Ingredients Berry: Durin Berry ×1 Primary ingredient : Snoozy Tomato ×2 Possible ingredients : Snoozy Tomato Soft Potato Large Leek Main skill : Charge Energy S Base carry limit: 17 Restores 12 Energy to the user. Even while asleep, it appears that Victreebel opens its mouth wide to attract prey with the nectar-like acid within it. On very rare occasions, it seems to forget about luring in prey and instead sleeps face down. Shuddering Sleep Vine-Held Sleep Overturned Sleep Atop-Belly Sleep ★ ★★★★ ★★ ★★★ ★★★ ★★ ★★★★ ★ Mega Victreebel [ edit | edit source ] Pokémon GO Base HP: 190 Base Attack: 265 Base Defense: 181 Egg Distance: N/A Buddy Distance: 3 km Evolution Requirement: N/A Fast Attacks: Razor Leaf , Acid , Magical Leaf † Charged Attacks: Leaf Blade , Sludge Bomb , Solar Beam , Leaf Tornado , Acid Spray , Return Form data [ edit | edit source ] Mega Evolution [ edit | edit source ] Default Victreebel Victreebel Grass Poison Victreebelite ↔ Held Victreebelite Mega Victreebel Victreebel Grass Poison Evolution data [ edit | edit source ] Unevolved Bellsprout Grass Poison Level 21 → First Evolution Weepinbell Grass Poison Leaf Stone → Second Evolution Victreebel Grass Poison Sprites [ edit | edit source ] Generation I Red Green Red Blue Yellow Front Back Front Back Front Back Generation II Gold Silver Crystal Front Back Front Back Front Back Generation III Ruby Sapphire Emerald FireRed LeafGreen Front Back Front Back Front Back Generation IV Diamond Pearl Platinum HeartGold SoulSilver Front Back Front Back Front Back Generation V Black White Black 2 White 2 Front Back Front Back Generation VI X Y Omega Ruby Alpha Sapphire Front Back Front Back Generation VII Sun Moon Ultra Sun Ultra Moon Front Back Front Back Let's Go, Pikachu! Let's Go, Eevee! Cross-Generation HOME For other sprites and images, please see Victreebel images on the Bulbagarden Archives ."
    },
    {
      "title": "Pokédex entries",
      "text": "Pokédex entries [ edit | edit source ] Generation I Kanto #071 Red (JPN) (This entry was originally untranslated in English until it was reused in Pokémon FireRed .) Green Red (ENG) Said to live in huge colonies deep in jungles, although no one has ever returned from there. Blue Yellow Lures prey with the sweet aroma of honey. Swallowed whole, the prey is melted in a day, bones and all. Stadium Attracts prey with sweet-smelling honey. Its prey include bugs, naturally, and even large animals on occasion. Generation II Johto #066 Gold Acid that has dissolved many prey becomes sweeter, making it even more effective at attracting prey. Silver This horrifying plant Pok é mon attracts prey with aromatic honey, then melts them in its mouth. Crystal Once ingested into this Pok é mon 's body, even the hardest object will melt into nothing. Stadium 2 Acid that has dissolved many prey becomes sweeter, making it even more effective at attracting prey. (Pokémon Red, Silver, or Crystal inserted) This horrifying plant Pok é mon attracts prey with aromatic honey, then melts them in its mouth. (Pokémon Blue, Gold, or Yellow inserted) Generation III Hoenn #— Kanto #071 Ruby Victreebel has a long vine that extends from its head. This vine is waved and flicked about as if it were an animal to attract prey. When an unsuspecting prey draws near, this Pok é mon swallows it whole. Sapphire Emerald The long vine extending from its head is waved about as if it were a living thing to attract prey. When an unsuspecting victim approaches, it is swallowed whole. FireRed Lures prey into its mouth with a honeylike aroma. The helpless prey is melted with a dissolving fluid. LeafGreen Said to live in huge colonies deep in jungles, although no one has ever returned from there. Generation IV Sinnoh #— Johto #066 Diamond It pools in its mouth a fluid with a honeylike scent, which is really an acid that dissolves anything. Pearl Platinum HeartGold Acid that has dissolved many prey becomes sweeter, making it even more effective at attracting prey. SoulSilver This horrifying plant Pokémon attracts prey with aromatic honey, then melts them in its mouth. Generation V Unova #— Black It pools in its mouth a fluid with a honeylike scent, which is really an acid that dissolves anything. White Black 2 It pools in its mouth a fluid with a honey-like scent, which is really an acid that dissolves anything. White 2 Generation VI Central Kalos #— Coastal Kalos #— Mountain Kalos #028 Hoenn #— X Said to live in huge colonies deep in jungles, although no one has ever returned from there. Y Once ingested into this Pokémon's body, even the hardest object will melt into nothing. Omega Ruby Victreebel has a long vine that extends from its head. This vine is waved and flicked about as if it were an animal to attract prey. When an unsuspecting prey draws near, this Pokémon swallows it whole. Alpha Sapphire Generation VII Alola #— Kanto #071 This Pokémon has no Pokédex entries in Sun, Moon , Ultra Sun, and Ultra Moon . Let's Go Pikachu Lures prey with the sweet aroma of honey. Swallowed whole, the prey is dissolved in a day, bones and all. Let's Go Eevee Generation VIII Galar #— Isle of Armor #— Crown Tundra #— Sinnoh #— Hisui #— This Pokémon has no Pokédex entries in Sword, Shield , and Legends: Arceus . Brilliant Diamond In its mouth, it pools a fragrant nectar-like fluid. The fluid is really an acid that dissolves anything. Shining Pearl Generation IX Paldea #— Kitakami #25 Blueberry #— Lumiose #076 Hyperspace #— Scarlet It lures prey into its mouth with a nectar-like aroma. The helpless prey is melted with a dissolving fluid. Violet After dissolving many prey, this Pokémon's acid becomes sweeter. This makes it even easier to attract more prey. Legends: Z-A Once taken into Victreebel's body, even the hardest object will be melted into nothing by the Pokémon's acid. Mega Victreebel Legends: Z-A The volume of this Pokémon's acid has increased due to Mega Evolution, filling its mouth. If it's not careful, the acid will overflow and spill out. Spin-off games Pokopia #023 Pokopia After dissolving many prey, this Pokémon's acid becomes sweeter. This makes it even easier to attract more prey. Victreebel in the Kitakami Pokédex"
    },
    {
      "title": "Trivia",
      "text": "Contents 1 Trivia 1.1 Concept and development 1.2 Origin 1.2.1 Name origin Trivia [ edit | edit source ] In Generation I , Victreebel has the highest index number of all non- glitch Pokémon . Despite learning Leech Life through breeding , Victreebel and its pre-evolved forms could not learn it through TM until Pokémon Scarlet and Violet . In Pokémon Horizons: The Series , Brassius has made a pitcher modeled after a Victreebel. This could be a pun because it is based off of a pitcher plant. Mega Victreebel was first teased in a short video titled \"The Case of the Sweet Scent Incident\", which was released on August 21, 2025. [ 1 ] Concept and development [ edit | edit source ] Victreebel, along with its evolutionary relatives, was designed by Atsuko Nishida . [ 2 ] [ 3 ] Origin [ edit | edit source ] Bulbanews Bulbanews has an article related to this subject: On the Origin of Species: Victreebel Victreebel may be based on carnivorous pitcher plants . The blue lips in its Shiny coloration may reference how a pitcher plant's rim turns blue under UV light . Mega Victreebel may be based on the Nepenthes genus in particular — specifically their lower traps that tend to be larger and sit on the ground. The way Mega Victreebel's vine constricts its mouth shut may also be inspired by the coiling vines of several Nepenthes species such as Nepenthes mirabilis . Mega Victreebel also bears resemblance to calabashes (also known as \"bottle gourds\"), waterskins , or wineskins . It may also be based on water balloon yo-yos (Japanese: 水ヨーヨー mizu yo-yo ) used in the game of yo-yo fishing (Japanese: ヨーヨー釣り yo-yo tsuri ). Name origin [ edit | edit source ] Victreebel may be a combination of victory , tree , and bell . The removal of an L in \"bell\" is likely a result of the ten-character limit on English Pokémon names prior to Generation VI . Utsubot may be derived from 靫葛 utsubokazura (pitcher plant) and possibly ポット pot . ↑ (August 21, 2025). \" The Case of the Sweet Scent Incident | Pokémon Legends: Z-A .\" The Official Pokémon YouTube channel. YouTube . ↑ Interview with Atsuko Nishida on Game Freak's website (archived, Japanese) ↑ Fun's Project interview with Atsuko Nishida (Japanese)"
    }
  ],
  "familyPages": [],
  "titleCandidates": [
    "Victreebel",
    "Victreebel (Pokemon)",
    "Victreebel (Pokémon)",
    "Victreebel (species)"
  ],
  "updatedAt": 1773328302
}